setup.py
xpoint/__init__.py
xpoint/canvas.py
xpoint/part.py
xpoint/path.py
xpoint/point.py
xpoint/style.py
xpoint.egg-info/PKG-INFO
xpoint.egg-info/SOURCES.txt
xpoint.egg-info/dependency_links.txt
xpoint.egg-info/requires.txt
xpoint.egg-info/top_level.txt