Metadata-Version: 2.1
Name: xpoint
Version: 0.0.0
Summary: Library for 3D geometry
Home-page: https://github.com/rdemaria/xpoint
Author: Riccardo De Maria
Author-email: riccardodemaria@gmail.com
